[
  {
    "sub_level_domain": true,
    "source": "bfmtv.com",
    "recs": [
      {
        "certification_id": null,
        "publisher_id": "3179",
        "relationship": "DIRECT",
        "duplicated": false,
        "line": 0,
        "faults": [],
        "domain": "adstanding.com"
      },
      {
        "certification_id": null,
        "publisher_id": "1135.1",
        "relationship": "RESELLER",
        "duplicated": false,
        "line": 1,
        "faults": [],
        "domain": "adtech.com"
      },
      {
        "certification_id": null,
        "publisher_id": "26154",
        "relationship": "RESELLER",
        "duplicated": false,
        "line": 2,
        "faults": [],
        "domain": "advertising.com"
      },
      {
        "certification_id": null,
        "publisher_id": "28038",
        "relationship": "RESELLER",
        "duplicated": false,
        "line": 3,
        "faults": [],
        "domain": "advertising.com"
      },
      {
        "certification_id": "4ad745ead2958bf7",
        "publisher_id": "095b488441206fe2df327a0050e578a4",
        "relationship": "DIRECT",
        "duplicated": false,
        "line": 4,
        "faults": [],
        "domain": "adyoulike.com"
      },
      {
        "certification_id": null,
        "publisher_id": "662483e9c6600a0e9e743273545577f2",
        "relationship": "RESELLER",
        "duplicated": false,
        "line": 5,
        "faults": [],
        "domain": "adyoulike.com"
      },
      {
        "certification_id": null,
        "publisher_id": "ac29a43656efe7ec96ad4d1f42766f0b",
        "relationship": "RESELLER",
        "duplicated": false,
        "line": 6,
        "faults": [],
        "domain": "adyoulike.com"
      },
      {
        "certification_id": null,
        "publisher_id": "1135.1",
        "relationship": "RESELLER",
        "duplicated": false,
        "line": 7,
        "faults": [],
        "domain": "aolcloud.net"
      },
      {
        "certification_id": null,
        "publisher_id": "1314",
        "relationship": "RESELLER",
        "duplicated": false,
        "line": 8,
        "faults": [],
        "domain": "appnexus.com"
      },
      {
        "certification_id": "f5ab79cb980f11d1",
        "publisher_id": "1504",
        "relationship": "RESELLER",
        "duplicated": false,
        "line": 9,
        "faults": [],
        "domain": "appnexus.com"
      },
      {
        "certification_id": "f5ab79cb980f11d1",
        "publisher_id": "1608",
        "relationship": "RESELLER",
        "duplicated": false,
        "line": 10,
        "faults": [],
        "domain": "appnexus.com"
      },
      {
        "certification_id": null,
        "publisher_id": "1851",
        "relationship": "RESELLER",
        "duplicated": false,
        "line": 11,
        "faults": [],
        "domain": "appnexus.com"
      },
      {
        "certification_id": null,
        "publisher_id": "2579",
        "relationship": "DIRECT",
        "duplicated": false,
        "line": 12,
        "faults": [],
        "domain": "appnexus.com"
      },
      {
        "certification_id": "f5ab79cb980f11d1",
        "publisher_id": "3500",
        "relationship": "RESELLER",
        "duplicated": false,
        "line": 13,
        "faults": [],
        "domain": "appnexus.com"
      },
      {
        "certification_id": null,
        "publisher_id": "3528",
        "relationship": "RESELLER",
        "duplicated": false,
        "line": 14,
        "faults": [],
        "domain": "appnexus.com"
      },
      {
        "certification_id": null,
        "publisher_id": "3538",
        "relationship": "RESELLER",
        "duplicated": false,
        "line": 15,
        "faults": [],
        "domain": "appnexus.com"
      },
      {
        "certification_id": null,
        "publisher_id": "3539",
        "relationship": "RESELLER",
        "duplicated": false,
        "line": 16,
        "faults": [],
        "domain": "appnexus.com"
      },
      {
        "certification_id": null,
        "publisher_id": "3540",
        "relationship": "RESELLER",
        "duplicated": false,
        "line": 17,
        "faults": [],
        "domain": "appnexus.com"
      },
      {
        "certification_id": "f5ab79cb980f11d1",
        "publisher_id": "3703",
        "relationship": "DIRECT",
        "duplicated": false,
        "line": 18,
        "faults": [],
        "domain": "appnexus.com"
      },
      {
        "certification_id": "f5ab79cb980f11d1",
        "publisher_id": "3703",
        "relationship": "RESELLER",
        "duplicated": false,
        "line": 19,
        "faults": [],
        "domain": "appnexus.com"
      },
      {
        "certification_id": null,
        "publisher_id": "3741",
        "relationship": "RESELLER",
        "duplicated": false,
        "line": 20,
        "faults": [],
        "domain": "appnexus.com"
      },
      {
        "certification_id": null,
        "publisher_id": "3927",
        "relationship": "RESELLER",
        "duplicated": false,
        "line": 21,
        "faults": [],
        "domain": "appnexus.com"
      },
      {
        "certification_id": "f5ab79cb980f11d1",
        "publisher_id": "7597",
        "relationship": "RESELLER",
        "duplicated": false,
        "line": 22,
        "faults": [],
        "domain": "appnexus.com"
      },
      {
        "certification_id": "f5ab79cb980f11d1",
        "publisher_id": "8494",
        "relationship": "RESELLER",
        "duplicated": false,
        "line": 23,
        "faults": [],
        "domain": "appnexus.com"
      },
      {
        "certification_id": null,
        "publisher_id": "9242",
        "relationship": "RESELLER",
        "duplicated": false,
        "line": 24,
        "faults": [],
        "domain": "appnexus.com"
      },
      {
        "certification_id": null,
        "publisher_id": "3403",
        "relationship": "DIRECT",
        "duplicated": false,
        "line": 25,
        "faults": [],
        "domain": "aps.amazon.com"
      },
      {
        "certification_id": "89ff185a4c4e857c",
        "publisher_id": "560288",
        "relationship": "DIRECT",
        "duplicated": false,
        "line": 26,
        "faults": [],
        "domain": "contextweb.com"
      },
      {
        "certification_id": "89ff185a4c4e857c",
        "publisher_id": "560288",
        "relationship": "RESELLER",
        "duplicated": false,
        "line": 27,
        "faults": [],
        "domain": "contextweb.com"
      },
      {
        "certification_id": "89ff185a4c4e857c",
        "publisher_id": "562145",
        "relationship": "RESELLER",
        "duplicated": false,
        "line": 28,
        "faults": [],
        "domain": "contextweb.com"
      },
      {
        "certification_id": "3fd707be9c4527c3",
        "publisher_id": "101760",
        "relationship": "RESELLER",
        "duplicated": false,
        "line": 29,
        "faults": [],
        "domain": "districtm.io"
      },
      {
        "certification_id": null,
        "publisher_id": "10002",
        "relationship": "DIRECT",
        "duplicated": false,
        "line": 30,
        "faults": [],
        "domain": "freewheel.tv"
      },
      {
        "certification_id": null,
        "publisher_id": "1000353",
        "relationship": "DIRECT",
        "duplicated": false,
        "line": 31,
        "faults": [],
        "domain": "freewheel.tv"
      },
      {
        "certification_id": null,
        "publisher_id": "1036625",
        "relationship": "DIRECT",
        "duplicated": false,
        "line": 32,
        "faults": [],
        "domain": "freewheel.tv"
      },
      {
        "certification_id": null,
        "publisher_id": "1041073",
        "relationship": "DIRECT",
        "duplicated": false,
        "line": 33,
        "faults": [],
        "domain": "freewheel.tv"
      },
      {
        "certification_id": null,
        "publisher_id": "1041089",
        "relationship": "RESELLER",
        "duplicated": false,
        "line": 34,
        "faults": [],
        "domain": "freewheel.tv"
      },
      {
        "certification_id": null,
        "publisher_id": "1073089",
        "relationship": "RESELLER",
        "duplicated": false,
        "line": 35,
        "faults": [],
        "domain": "freewheel.tv"
      },
      {
        "certification_id": null,
        "publisher_id": "1073105",
        "relationship": "RESELLER",
        "duplicated": false,
        "line": 36,
        "faults": [],
        "domain": "freewheel.tv"
      },
      {
        "certification_id": null,
        "publisher_id": "1073121",
        "relationship": "RESELLER",
        "duplicated": false,
        "line": 37,
        "faults": [],
        "domain": "freewheel.tv"
      },
      {
        "certification_id": null,
        "publisher_id": "1073137",
        "relationship": "RESELLER",
        "duplicated": false,
        "line": 38,
        "faults": [],
        "domain": "freewheel.tv"
      },
      {
        "certification_id": null,
        "publisher_id": "1073153",
        "relationship": "RESELLER",
        "duplicated": false,
        "line": 39,
        "faults": [],
        "domain": "freewheel.tv"
      },
      {
        "certification_id": null,
        "publisher_id": "1073169",
        "relationship": "RESELLER",
        "duplicated": false,
        "line": 40,
        "faults": [],
        "domain": "freewheel.tv"
      },
      {
        "certification_id": null,
        "publisher_id": "1073185",
        "relationship": "RESELLER",
        "duplicated": false,
        "line": 41,
        "faults": [],
        "domain": "freewheel.tv"
      },
      {
        "certification_id": null,
        "publisher_id": "1073201",
        "relationship": "RESELLER",
        "duplicated": false,
        "line": 42,
        "faults": [],
        "domain": "freewheel.tv"
      },
      {
        "certification_id": null,
        "publisher_id": "1073217",
        "relationship": "RESELLER",
        "duplicated": false,
        "line": 43,
        "faults": [],
        "domain": "freewheel.tv"
      },
      {
        "certification_id": null,
        "publisher_id": "1073233",
        "relationship": "RESELLER",
        "duplicated": false,
        "line": 44,
        "faults": [],
        "domain": "freewheel.tv"
      },
      {
        "certification_id": null,
        "publisher_id": "122137",
        "relationship": "RESELLER",
        "duplicated": false,
        "line": 45,
        "faults": [],
        "domain": "freewheel.tv"
      },
      {
        "certification_id": null,
        "publisher_id": "132089",
        "relationship": "DIRECT",
        "duplicated": false,
        "line": 46,
        "faults": [],
        "domain": "freewheel.tv"
      },
      {
        "certification_id": null,
        "publisher_id": "132129",
        "relationship": "RESELLER",
        "duplicated": false,
        "line": 47,
        "faults": [],
        "domain": "freewheel.tv"
      },
      {
        "certification_id": null,
        "publisher_id": "150353",
        "relationship": "DIRECT",
        "duplicated": false,
        "line": 48,
        "faults": [],
        "domain": "freewheel.tv"
      },
      {
        "certification_id": null,
        "publisher_id": "150361",
        "relationship": "RESELLER",
        "duplicated": false,
        "line": 49,
        "faults": [],
        "domain": "freewheel.tv"
      },
      {
        "certification_id": null,
        "publisher_id": "184985",
        "relationship": "DIRECT",
        "duplicated": false,
        "line": 50,
        "faults": [],
        "domain": "freewheel.tv"
      },
      {
        "certification_id": null,
        "publisher_id": "184993",
        "relationship": "RESELLER",
        "duplicated": false,
        "line": 51,
        "faults": [],
        "domain": "freewheel.tv"
      },
      {
        "certification_id": null,
        "publisher_id": "185001",
        "relationship": "RESELLER",
        "duplicated": false,
        "line": 52,
        "faults": [],
        "domain": "freewheel.tv"
      },
      {
        "certification_id": null,
        "publisher_id": "185569",
        "relationship": "RESELLER",
        "duplicated": false,
        "line": 53,
        "faults": [],
        "domain": "freewheel.tv"
      },
      {
        "certification_id": null,
        "publisher_id": "187401",
        "relationship": "DIRECT",
        "duplicated": false,
        "line": 54,
        "faults": [],
        "domain": "freewheel.tv"
      },
      {
        "certification_id": null,
        "publisher_id": "187409",
        "relationship": "RESELLER",
        "duplicated": false,
        "line": 55,
        "faults": [],
        "domain": "freewheel.tv"
      },
      {
        "certification_id": null,
        "publisher_id": "187417",
        "relationship": "RESELLER",
        "duplicated": false,
        "line": 56,
        "faults": [],
        "domain": "freewheel.tv"
      },
      {
        "certification_id": null,
        "publisher_id": "187425",
        "relationship": "DIRECT",
        "duplicated": false,
        "line": 57,
        "faults": [],
        "domain": "freewheel.tv"
      },
      {
        "certification_id": null,
        "publisher_id": "187433",
        "relationship": "RESELLER",
        "duplicated": false,
        "line": 58,
        "faults": [],
        "domain": "freewheel.tv"
      },
      {
        "certification_id": null,
        "publisher_id": "187441",
        "relationship": "RESELLER",
        "duplicated": false,
        "line": 59,
        "faults": [],
        "domain": "freewheel.tv"
      },
      {
        "certification_id": null,
        "publisher_id": "188769",
        "relationship": "DIRECT",
        "duplicated": false,
        "line": 60,
        "faults": [],
        "domain": "freewheel.tv"
      },
      {
        "certification_id": null,
        "publisher_id": "188777",
        "relationship": "RESELLER",
        "duplicated": false,
        "line": 61,
        "faults": [],
        "domain": "freewheel.tv"
      },
      {
        "certification_id": null,
        "publisher_id": "188785",
        "relationship": "RESELLER",
        "duplicated": false,
        "line": 62,
        "faults": [],
        "domain": "freewheel.tv"
      },
      {
        "certification_id": null,
        "publisher_id": "188801",
        "relationship": "DIRECT",
        "duplicated": false,
        "line": 63,
        "faults": [],
        "domain": "freewheel.tv"
      },
      {
        "certification_id": null,
        "publisher_id": "188809",
        "relationship": "RESELLER",
        "duplicated": false,
        "line": 64,
        "faults": [],
        "domain": "freewheel.tv"
      },
      {
        "certification_id": null,
        "publisher_id": "188817",
        "relationship": "RESELLER",
        "duplicated": false,
        "line": 65,
        "faults": [],
        "domain": "freewheel.tv"
      },
      {
        "certification_id": null,
        "publisher_id": "189081",
        "relationship": "DIRECT",
        "duplicated": false,
        "line": 66,
        "faults": [],
        "domain": "freewheel.tv"
      },
      {
        "certification_id": null,
        "publisher_id": "189089",
        "relationship": "RESELLER",
        "duplicated": false,
        "line": 67,
        "faults": [],
        "domain": "freewheel.tv"
      },
      {
        "certification_id": null,
        "publisher_id": "189097",
        "relationship": "RESELLER",
        "duplicated": false,
        "line": 68,
        "faults": [],
        "domain": "freewheel.tv"
      },
      {
        "certification_id": null,
        "publisher_id": "203265",
        "relationship": "DIRECT",
        "duplicated": false,
        "line": 69,
        "faults": [],
        "domain": "freewheel.tv"
      },
      {
        "certification_id": null,
        "publisher_id": "213562",
        "relationship": "RESELLER",
        "duplicated": false,
        "line": 70,
        "faults": [],
        "domain": "freewheel.tv"
      },
      {
        "certification_id": null,
        "publisher_id": "213594",
        "relationship": "RESELLER",
        "duplicated": false,
        "line": 71,
        "faults": [],
        "domain": "freewheel.tv"
      },
      {
        "certification_id": null,
        "publisher_id": "213626",
        "relationship": "RESELLER",
        "duplicated": false,
        "line": 72,
        "faults": [],
        "domain": "freewheel.tv"
      },
      {
        "certification_id": null,
        "publisher_id": "213650",
        "relationship": "RESELLER",
        "duplicated": false,
        "line": 73,
        "faults": [],
        "domain": "freewheel.tv"
      },
      {
        "certification_id": null,
        "publisher_id": "213674",
        "relationship": "RESELLER",
        "duplicated": false,
        "line": 74,
        "faults": [],
        "domain": "freewheel.tv"
      },
      {
        "certification_id": null,
        "publisher_id": "213706",
        "relationship": "RESELLER",
        "duplicated": false,
        "line": 75,
        "faults": [],
        "domain": "freewheel.tv"
      },
      {
        "certification_id": null,
        "publisher_id": "216314",
        "relationship": "DIRECT",
        "duplicated": false,
        "line": 76,
        "faults": [],
        "domain": "freewheel.tv"
      },
      {
        "certification_id": null,
        "publisher_id": "216322",
        "relationship": "RESELLER",
        "duplicated": false,
        "line": 77,
        "faults": [],
        "domain": "freewheel.tv"
      },
      {
        "certification_id": null,
        "publisher_id": "216330",
        "relationship": "RESELLER",
        "duplicated": false,
        "line": 78,
        "faults": [],
        "domain": "freewheel.tv"
      },
      {
        "certification_id": null,
        "publisher_id": "216602",
        "relationship": "RESELLER",
        "duplicated": false,
        "line": 79,
        "faults": [],
        "domain": "freewheel.tv"
      },
      {
        "certification_id": null,
        "publisher_id": "216618",
        "relationship": "RESELLER",
        "duplicated": false,
        "line": 80,
        "faults": [],
        "domain": "freewheel.tv"
      },
      {
        "certification_id": null,
        "publisher_id": "220018",
        "relationship": "RESELLER",
        "duplicated": false,
        "line": 81,
        "faults": [],
        "domain": "freewheel.tv"
      },
      {
        "certification_id": null,
        "publisher_id": "22289",
        "relationship": "RESELLER",
        "duplicated": false,
        "line": 82,
        "faults": [],
        "domain": "freewheel.tv"
      },
      {
        "certification_id": null,
        "publisher_id": "22293",
        "relationship": "RESELLER",
        "duplicated": false,
        "line": 83,
        "faults": [],
        "domain": "freewheel.tv"
      },
      {
        "certification_id": null,
        "publisher_id": "22297",
        "relationship": "RESELLER",
        "duplicated": false,
        "line": 84,
        "faults": [],
        "domain": "freewheel.tv"
      },
      {
        "certification_id": null,
        "publisher_id": "22301",
        "relationship": "RESELLER",
        "duplicated": false,
        "line": 85,
        "faults": [],
        "domain": "freewheel.tv"
      },
      {
        "certification_id": null,
        "publisher_id": "22305",
        "relationship": "RESELLER",
        "duplicated": false,
        "line": 86,
        "faults": [],
        "domain": "freewheel.tv"
      },
      {
        "certification_id": null,
        "publisher_id": "225769",
        "relationship": "DIRECT",
        "duplicated": false,
        "line": 87,
        "faults": [],
        "domain": "freewheel.tv"
      },
      {
        "certification_id": null,
        "publisher_id": "225777",
        "relationship": "RESELLER",
        "duplicated": false,
        "line": 88,
        "faults": [],
        "domain": "freewheel.tv"
      },
      {
        "certification_id": null,
        "publisher_id": "227409",
        "relationship": "DIRECT",
        "duplicated": false,
        "line": 89,
        "faults": [],
        "domain": "freewheel.tv"
      },
      {
        "certification_id": null,
        "publisher_id": "227417",
        "relationship": "RESELLER",
        "duplicated": false,
        "line": 90,
        "faults": [],
        "domain": "freewheel.tv"
      },
      {
        "certification_id": null,
        "publisher_id": "227425",
        "relationship": "RESELLER",
        "duplicated": false,
        "line": 91,
        "faults": [],
        "domain": "freewheel.tv"
      },
      {
        "certification_id": null,
        "publisher_id": "227441",
        "relationship": "RESELLER",
        "duplicated": false,
        "line": 92,
        "faults": [],
        "domain": "freewheel.tv"
      },
      {
        "certification_id": null,
        "publisher_id": "227465",
        "relationship": "RESELLER",
        "duplicated": false,
        "line": 93,
        "faults": [],
        "domain": "freewheel.tv"
      },
      {
        "certification_id": null,
        "publisher_id": "227489",
        "relationship": "RESELLER",
        "duplicated": false,
        "line": 94,
        "faults": [],
        "domain": "freewheel.tv"
      },
      {
        "certification_id": null,
        "publisher_id": "227529",
        "relationship": "RESELLER",
        "duplicated": false,
        "line": 95,
        "faults": [],
        "domain": "freewheel.tv"
      },
      {
        "certification_id": null,
        "publisher_id": "227553",
        "relationship": "RESELLER",
        "duplicated": false,
        "line": 96,
        "faults": [],
        "domain": "freewheel.tv"
      },
      {
        "certification_id": null,
        "publisher_id": "231689",
        "relationship": "DIRECT",
        "duplicated": false,
        "line": 97,
        "faults": [],
        "domain": "freewheel.tv"
      },
      {
        "certification_id": null,
        "publisher_id": "231697",
        "relationship": "RESELLER",
        "duplicated": false,
        "line": 98,
        "faults": [],
        "domain": "freewheel.tv"
      },
      {
        "certification_id": null,
        "publisher_id": "231705",
        "relationship": "RESELLER",
        "duplicated": false,
        "line": 99,
        "faults": [],
        "domain": "freewheel.tv"
      },
      {
        "certification_id": null,
        "publisher_id": "233409",
        "relationship": "RESELLER",
        "duplicated": false,
        "line": 100,
        "faults": [],
        "domain": "freewheel.tv"
      },
      {
        "certification_id": null,
        "publisher_id": "234641",
        "relationship": "DIRECT",
        "duplicated": false,
        "line": 101,
        "faults": [],
        "domain": "freewheel.tv"
      },
      {
        "certification_id": null,
        "publisher_id": "234649",
        "relationship": "DIRECT",
        "duplicated": false,
        "line": 102,
        "faults": [],
        "domain": "freewheel.tv"
      },
      {
        "certification_id": null,
        "publisher_id": "234657",
        "relationship": "RESELLER",
        "duplicated": false,
        "line": 103,
        "faults": [],
        "domain": "freewheel.tv"
      },
      {
        "certification_id": null,
        "publisher_id": "234665",
        "relationship": "RESELLER",
        "duplicated": false,
        "line": 104,
        "faults": [],
        "domain": "freewheel.tv"
      },
      {
        "certification_id": null,
        "publisher_id": "234673",
        "relationship": "RESELLER",
        "duplicated": false,
        "line": 105,
        "faults": [],
        "domain": "freewheel.tv"
      },
      {
        "certification_id": null,
        "publisher_id": "234681",
        "relationship": "RESELLER",
        "duplicated": false,
        "line": 106,
        "faults": [],
        "domain": "freewheel.tv"
      },
      {
        "certification_id": null,
        "publisher_id": "258578",
        "relationship": "RESELLER",
        "duplicated": false,
        "line": 107,
        "faults": [],
        "domain": "freewheel.tv"
      },
      {
        "certification_id": null,
        "publisher_id": "273986",
        "relationship": "DIRECT",
        "duplicated": false,
        "line": 108,
        "faults": [],
        "domain": "freewheel.tv"
      },
      {
        "certification_id": null,
        "publisher_id": "274002",
        "relationship": "RESELLER",
        "duplicated": false,
        "line": 109,
        "faults": [],
        "domain": "freewheel.tv"
      },
      {
        "certification_id": null,
        "publisher_id": "274018",
        "relationship": "RESELLER",
        "duplicated": false,
        "line": 110,
        "faults": [],
        "domain": "freewheel.tv"
      },
      {
        "certification_id": null,
        "publisher_id": "274034",
        "relationship": "DIRECT",
        "duplicated": false,
        "line": 111,
        "faults": [],
        "domain": "freewheel.tv"
      },
      {
        "certification_id": null,
        "publisher_id": "274050",
        "relationship": "RESELLER",
        "duplicated": false,
        "line": 112,
        "faults": [],
        "domain": "freewheel.tv"
      },
      {
        "certification_id": null,
        "publisher_id": "274834",
        "relationship": "DIRECT",
        "duplicated": false,
        "line": 113,
        "faults": [],
        "domain": "freewheel.tv"
      },
      {
        "certification_id": null,
        "publisher_id": "274850",
        "relationship": "RESELLER",
        "duplicated": false,
        "line": 114,
        "faults": [],
        "domain": "freewheel.tv"
      },
      {
        "certification_id": null,
        "publisher_id": "274866",
        "relationship": "RESELLER",
        "duplicated": false,
        "line": 115,
        "faults": [],
        "domain": "freewheel.tv"
      },
      {
        "certification_id": null,
        "publisher_id": "321761",
        "relationship": "DIRECT",
        "duplicated": false,
        "line": 116,
        "faults": [],
        "domain": "freewheel.tv"
      },
      {
        "certification_id": null,
        "publisher_id": "321777",
        "relationship": "RESELLER",
        "duplicated": false,
        "line": 117,
        "faults": [],
        "domain": "freewheel.tv"
      },
      {
        "certification_id": null,
        "publisher_id": "321793",
        "relationship": "RESELLER",
        "duplicated": false,
        "line": 118,
        "faults": [],
        "domain": "freewheel.tv"
      },
      {
        "certification_id": null,
        "publisher_id": "379057",
        "relationship": "DIRECT",
        "duplicated": false,
        "line": 119,
        "faults": [],
        "domain": "freewheel.tv"
      },
      {
        "certification_id": null,
        "publisher_id": "379073",
        "relationship": "RESELLER",
        "duplicated": false,
        "line": 120,
        "faults": [],
        "domain": "freewheel.tv"
      },
      {
        "certification_id": null,
        "publisher_id": "38121",
        "relationship": "DIRECT",
        "duplicated": false,
        "line": 121,
        "faults": [],
        "domain": "freewheel.tv"
      },
      {
        "certification_id": null,
        "publisher_id": "38129",
        "relationship": "RESELLER",
        "duplicated": false,
        "line": 122,
        "faults": [],
        "domain": "freewheel.tv"
      },
      {
        "certification_id": null,
        "publisher_id": "38137",
        "relationship": "RESELLER",
        "duplicated": false,
        "line": 123,
        "faults": [],
        "domain": "freewheel.tv"
      },
      {
        "certification_id": null,
        "publisher_id": "52425",
        "relationship": "RESELLER",
        "duplicated": false,
        "line": 124,
        "faults": [],
        "domain": "freewheel.tv"
      },
      {
        "certification_id": null,
        "publisher_id": "52449",
        "relationship": "RESELLER",
        "duplicated": false,
        "line": 125,
        "faults": [],
        "domain": "freewheel.tv"
      },
      {
        "certification_id": null,
        "publisher_id": "53113",
        "relationship": "RESELLER",
        "duplicated": false,
        "line": 126,
        "faults": [],
        "domain": "freewheel.tv"
      },
      {
        "certification_id": null,
        "publisher_id": "53321",
        "relationship": "RESELLER",
        "duplicated": false,
        "line": 127,
        "faults": [],
        "domain": "freewheel.tv"
      },
      {
        "certification_id": null,
        "publisher_id": "66905",
        "relationship": "RESELLER",
        "duplicated": false,
        "line": 128,
        "faults": [],
        "domain": "freewheel.tv"
      },
      {
        "certification_id": null,
        "publisher_id": "68025",
        "relationship": "RESELLER",
        "duplicated": false,
        "line": 129,
        "faults": [],
        "domain": "freewheel.tv"
      },
      {
        "certification_id": null,
        "publisher_id": "704914",
        "relationship": "DIRECT",
        "duplicated": false,
        "line": 130,
        "faults": [],
        "domain": "freewheel.tv"
      },
      {
        "certification_id": null,
        "publisher_id": "708402",
        "relationship": "RESELLER",
        "duplicated": false,
        "line": 131,
        "faults": [],
        "domain": "freewheel.tv"
      },
      {
        "certification_id": null,
        "publisher_id": "709586",
        "relationship": "RESELLER",
        "duplicated": false,
        "line": 132,
        "faults": [],
        "domain": "freewheel.tv"
      },
      {
        "certification_id": null,
        "publisher_id": "709602",
        "relationship": "RESELLER",
        "duplicated": false,
        "line": 133,
        "faults": [],
        "domain": "freewheel.tv"
      },
      {
        "certification_id": null,
        "publisher_id": "710210",
        "relationship": "DIRECT",
        "duplicated": false,
        "line": 134,
        "faults": [],
        "domain": "freewheel.tv"
      },
      {
        "certification_id": null,
        "publisher_id": "710226",
        "relationship": "RESELLER",
        "duplicated": false,
        "line": 135,
        "faults": [],
        "domain": "freewheel.tv"
      },
      {
        "certification_id": null,
        "publisher_id": "720722",
        "relationship": "DIRECT",
        "duplicated": false,
        "line": 136,
        "faults": [],
        "domain": "freewheel.tv"
      },
      {
        "certification_id": null,
        "publisher_id": "720738",
        "relationship": "RESELLER",
        "duplicated": false,
        "line": 137,
        "faults": [],
        "domain": "freewheel.tv"
      },
      {
        "certification_id": null,
        "publisher_id": "726594",
        "relationship": "DIRECT",
        "duplicated": false,
        "line": 138,
        "faults": [],
        "domain": "freewheel.tv"
      },
      {
        "certification_id": null,
        "publisher_id": "726610",
        "relationship": "RESELLER",
        "duplicated": false,
        "line": 139,
        "faults": [],
        "domain": "freewheel.tv"
      },
      {
        "certification_id": null,
        "publisher_id": "732290",
        "relationship": "DIRECT",
        "duplicated": false,
        "line": 140,
        "faults": [],
        "domain": "freewheel.tv"
      },
      {
        "certification_id": null,
        "publisher_id": "732306",
        "relationship": "DIRECT",
        "duplicated": false,
        "line": 141,
        "faults": [],
        "domain": "freewheel.tv"
      },
      {
        "certification_id": null,
        "publisher_id": "732322",
        "relationship": "RESELLER",
        "duplicated": false,
        "line": 142,
        "faults": [],
        "domain": "freewheel.tv"
      },
      {
        "certification_id": null,
        "publisher_id": "732338",
        "relationship": "RESELLER",
        "duplicated": false,
        "line": 143,
        "faults": [],
        "domain": "freewheel.tv"
      },
      {
        "certification_id": null,
        "publisher_id": "741650",
        "relationship": "RESELLER",
        "num_faults": 1,
        "duplicated": false,
        "line": 144,
        "faults": [
          {
            "level": 2,
            "reason": "Domain: Must be in lower case: Freewheel.tv",
            "hint": "freewheel.tv"
          }
        ],
        "domain": "Freewheel.tv"
      },
      {
        "certification_id": null,
        "publisher_id": "785009",
        "relationship": "DIRECT",
        "duplicated": false,
        "line": 145,
        "faults": [],
        "domain": "freewheel.tv"
      },
      {
        "certification_id": null,
        "publisher_id": "836497",
        "relationship": "DIRECT",
        "duplicated": false,
        "line": 146,
        "faults": [],
        "domain": "freewheel.tv"
      },
      {
        "certification_id": null,
        "publisher_id": "836513",
        "relationship": "RESELLER",
        "duplicated": false,
        "line": 147,
        "faults": [],
        "domain": "freewheel.tv"
      },
      {
        "certification_id": null,
        "publisher_id": "888689",
        "relationship": "DIRECT",
        "duplicated": false,
        "line": 148,
        "faults": [],
        "domain": "freewheel.tv"
      },
      {
        "certification_id": null,
        "publisher_id": "888705",
        "relationship": "RESELLER",
        "duplicated": false,
        "line": 149,
        "faults": [],
        "domain": "freewheel.tv"
      },
      {
        "certification_id": null,
        "publisher_id": "898353",
        "relationship": "DIRECT",
        "duplicated": false,
        "line": 150,
        "faults": [],
        "domain": "freewheel.tv"
      },
      {
        "certification_id": null,
        "publisher_id": "908337",
        "relationship": "DIRECT",
        "duplicated": false,
        "line": 151,
        "faults": [],
        "domain": "freewheel.tv"
      },
      {
        "certification_id": null,
        "publisher_id": "992465",
        "relationship": "RESELLER",
        "duplicated": false,
        "line": 152,
        "faults": [],
        "domain": "freewheel.tv"
      },
      {
        "certification_id": null,
        "publisher_id": "992481",
        "relationship": "RESELLER",
        "duplicated": false,
        "line": 153,
        "faults": [],
        "domain": "freewheel.tv"
      },
      {
        "certification_id": null,
        "publisher_id": "992497",
        "relationship": "RESELLER",
        "duplicated": false,
        "line": 154,
        "faults": [],
        "domain": "freewheel.tv"
      },
      {
        "certification_id": null,
        "publisher_id": "992513",
        "relationship": "RESELLER",
        "duplicated": false,
        "line": 155,
        "faults": [],
        "domain": "freewheel.tv"
      },
      {
        "certification_id": null,
        "publisher_id": "992529",
        "relationship": "RESELLER",
        "duplicated": false,
        "line": 156,
        "faults": [],
        "domain": "freewheel.tv"
      },
      {
        "certification_id": null,
        "publisher_id": "992545",
        "relationship": "RESELLER",
        "duplicated": false,
        "line": 157,
        "faults": [],
        "domain": "freewheel.tv"
      },
      {
        "certification_id": null,
        "publisher_id": "997745",
        "relationship": "DIRECT",
        "duplicated": false,
        "line": 158,
        "faults": [],
        "domain": "freewheel.tv"
      },
      {
        "certification_id": null,
        "publisher_id": "997777",
        "relationship": "DIRECT",
        "duplicated": false,
        "line": 159,
        "faults": [],
        "domain": "freewheel.tv"
      },
      {
        "certification_id": null,
        "publisher_id": "997809",
        "relationship": "DIRECT",
        "duplicated": false,
        "line": 160,
        "faults": [],
        "domain": "freewheel.tv"
      },
      {
        "certification_id": null,
        "publisher_id": "997841",
        "relationship": "DIRECT",
        "duplicated": false,
        "line": 161,
        "faults": [],
        "domain": "freewheel.tv"
      },
      {
        "certification_id": null,
        "publisher_id": "997873",
        "relationship": "DIRECT",
        "duplicated": false,
        "line": 162,
        "faults": [],
        "domain": "freewheel.tv"
      },
      {
        "certification_id": null,
        "publisher_id": "997905",
        "relationship": "DIRECT",
        "duplicated": false,
        "line": 163,
        "faults": [],
        "domain": "freewheel.tv"
      },
      {
        "certification_id": null,
        "publisher_id": "997937",
        "relationship": "DIRECT",
        "duplicated": false,
        "line": 164,
        "faults": [],
        "domain": "freewheel.tv"
      },
      {
        "certification_id": "f08c47fec0942fa0",
        "publisher_id": "pub-2236218997769327",
        "relationship": "DIRECT",
        "duplicated": false,
        "line": 165,
        "faults": [],
        "domain": "google.com"
      },
      {
        "certification_id": "f08c47fec0942fa0",
        "publisher_id": "pub-2366164365855963",
        "relationship": "RESELLER",
        "duplicated": false,
        "line": 166,
        "faults": [],
        "domain": "google.com"
      },
      {
        "certification_id": null,
        "publisher_id": "pub-3057818873023700",
        "relationship": "RESELLER",
        "duplicated": false,
        "line": 167,
        "faults": [],
        "domain": "google.com"
      },
      {
        "certification_id": "f08c47fec0942fa0",
        "publisher_id": "pub-3282595691941563",
        "relationship": "DIRECT",
        "duplicated": false,
        "line": 168,
        "faults": [],
        "domain": "google.com"
      },
      {
        "certification_id": "f08c47fec0942fa0",
        "publisher_id": "pub-3391936129161967",
        "relationship": "RESELLER",
        "duplicated": false,
        "line": 169,
        "faults": [],
        "domain": "google.com"
      },
      {
        "certification_id": "f08c47fec0942fa0",
        "publisher_id": "pub-5603862283412750",
        "relationship": "DIRECT",
        "duplicated": false,
        "line": 170,
        "faults": [],
        "domain": "google.com"
      },
      {
        "certification_id": "f08c47fec0942fa0",
        "publisher_id": "pub-6228005252642587",
        "relationship": "RESELLER",
        "duplicated": false,
        "line": 171,
        "faults": [],
        "domain": "google.com"
      },
      {
        "certification_id": "f08c47fec0942fa0",
        "publisher_id": "pub-9485981123373313",
        "relationship": "RESELLER",
        "duplicated": false,
        "line": 172,
        "faults": [],
        "domain": "google.com"
      },
      {
        "certification_id": "ffdef49475d318a9",
        "publisher_id": "13244",
        "relationship": "DIRECT",
        "duplicated": false,
        "line": 173,
        "faults": [],
        "domain": "gumgum.com"
      },
      {
        "certification_id": null,
        "publisher_id": "01BYK28ENND8X5G8K0AJ2DPK4E",
        "relationship": "DIRECT",
        "duplicated": false,
        "line": 174,
        "faults": [],
        "domain": "hubvisor.io"
      },
      {
        "certification_id": null,
        "publisher_id": "1005",
        "relationship": "RESELLER",
        "duplicated": false,
        "line": 175,
        "faults": [],
        "domain": "improvedigital.com"
      },
      {
        "certification_id": null,
        "publisher_id": "1006",
        "relationship": "DIRECT",
        "duplicated": false,
        "line": 176,
        "faults": [],
        "domain": "improvedigital.com"
      },
      {
        "certification_id": null,
        "publisher_id": "1067",
        "relationship": "RESELLER",
        "duplicated": false,
        "line": 177,
        "faults": [],
        "domain": "improvedigital.com"
      },
      {
        "certification_id": null,
        "publisher_id": "1220",
        "relationship": "RESELLER",
        "duplicated": false,
        "line": 178,
        "faults": [],
        "domain": "improvedigital.com"
      },
      {
        "certification_id": null,
        "publisher_id": "335",
        "relationship": "RESELLER",
        "duplicated": false,
        "line": 179,
        "faults": [],
        "domain": "improvedigital.com"
      },
      {
        "certification_id": "50b1c356f2c5c8fc",
        "publisher_id": "184665",
        "relationship": "RESELLER",
        "duplicated": false,
        "line": 180,
        "faults": [],
        "domain": "indexexchange.com"
      },
      {
        "certification_id": null,
        "publisher_id": "186401",
        "relationship": "DIRECT",
        "duplicated": false,
        "line": 181,
        "faults": [],
        "domain": "indexexchange.com"
      },
      {
        "certification_id": null,
        "publisher_id": "187149",
        "relationship": "RESELLER",
        "duplicated": false,
        "line": 182,
        "faults": [],
        "domain": "indexexchange.com"
      },
      {
        "certification_id": "50b1c356f2c5c8fc",
        "publisher_id": "188398",
        "relationship": "RESELLER",
        "duplicated": false,
        "line": 183,
        "faults": [],
        "domain": "indexexchange.com"
      },
      {
        "certification_id": "50b1c356f2c5c8fc",
        "publisher_id": "190856",
        "relationship": "RESELLER",
        "duplicated": false,
        "line": 184,
        "faults": [],
        "domain": "indexexchange.com"
      },
      {
        "certification_id": null,
        "publisher_id": "192098",
        "relationship": "DIRECT",
        "duplicated": false,
        "line": 185,
        "faults": [],
        "domain": "indexexchange.com"
      },
      {
        "certification_id": "59c49fa9598a0117",
        "publisher_id": "450",
        "relationship": "RESELLER",
        "duplicated": false,
        "line": 186,
        "faults": [],
        "domain": "lkqd.net"
      },
      {
        "certification_id": "6c8d5f95897a5a3b",
        "publisher_id": "5679",
        "relationship": "RESELLER",
        "duplicated": false,
        "line": 187,
        "faults": [],
        "domain": "loopme.com"
      },
      {
        "certification_id": "6c8d5f95897a5a3b",
        "publisher_id": "s-2411",
        "relationship": "RESELLER",
        "duplicated": false,
        "line": 188,
        "faults": [],
        "domain": "loopme.com"
      },
      {
        "certification_id": "6a698e2ec38604c6",
        "publisher_id": "537149888",
        "relationship": "DIRECT",
        "duplicated": false,
        "line": 189,
        "faults": [],
        "domain": "openx.com"
      },
      {
        "certification_id": "6a698e2ec38604c6",
        "publisher_id": "537149888",
        "relationship": "RESELLER",
        "duplicated": false,
        "line": 190,
        "faults": [],
        "domain": "openx.com"
      },
      {
        "certification_id": "6a698e2ec38604c6",
        "publisher_id": "540393169",
        "relationship": "RESELLER",
        "duplicated": false,
        "line": 191,
        "faults": [],
        "domain": "openx.com"
      },
      {
        "certification_id": "6a698e2ec38604c6",
        "publisher_id": "540841669",
        "relationship": "DIRECT",
        "duplicated": false,
        "line": 192,
        "faults": [],
        "domain": "openx.com"
      },
      {
        "certification_id": null,
        "publisher_id": "0018d4c057c1495c47f745e00c9eed4398",
        "relationship": "DIRECT",
        "duplicated": false,
        "line": 193,
        "faults": [],
        "domain": "outbrain.com"
      },
      {
        "certification_id": null,
        "publisher_id": "009ab4684af9e38d08e81127150fac245b",
        "relationship": "DIRECT",
        "duplicated": false,
        "line": 194,
        "faults": [],
        "domain": "outbrain.com"
      },
      {
        "certification_id": null,
        "publisher_id": "154037",
        "relationship": "RESELLER",
        "duplicated": false,
        "line": 195,
        "faults": [],
        "domain": "pubmatic.com"
      },
      {
        "certification_id": "5d62403b186f2ace",
        "publisher_id": "156431",
        "relationship": "RESELLER",
        "duplicated": false,
        "line": 196,
        "faults": [],
        "domain": "pubmatic.com"
      },
      {
        "certification_id": "5d62403b186f2ace",
        "publisher_id": "156431",
        "relationship": "RESELLER",
        "duplicated": true,
        "line": 197,
        "faults": [],
        "domain": "pubmatic.com"
      },
      {
        "certification_id": null,
        "publisher_id": "156439",
        "relationship": "RESELLER",
        "duplicated": false,
        "line": 198,
        "faults": [],
        "domain": "pubmatic.com"
      },
      {
        "certification_id": "5d62403b186f2ace",
        "publisher_id": "158615",
        "relationship": "RESELLER",
        "duplicated": false,
        "line": 199,
        "faults": [],
        "domain": "pubmatic.com"
      },
      {
        "certification_id": null,
        "publisher_id": "1778",
        "relationship": "DIRECT",
        "duplicated": false,
        "line": 200,
        "faults": [],
        "domain": "quantum-advertising.com"
      },
      {
        "certification_id": null,
        "publisher_id": "6071",
        "relationship": "DIRECT",
        "duplicated": false,
        "line": 201,
        "faults": [],
        "domain": "quantum-advertising.com"
      },
      {
        "certification_id": "0bfd66d529a55807",
        "publisher_id": "10027",
        "relationship": "RESELLER",
        "duplicated": false,
        "line": 202,
        "faults": [],
        "domain": "rubiconproject.com"
      },
      {
        "certification_id": null,
        "publisher_id": "12338",
        "relationship": "RESELLER",
        "duplicated": false,
        "line": 203,
        "faults": [],
        "domain": "rubiconproject.com"
      },
      {
        "certification_id": "0bfd66d529a55807",
        "publisher_id": "14976",
        "relationship": "DIRECT",
        "duplicated": false,
        "line": 204,
        "faults": [],
        "domain": "rubiconproject.com"
      },
      {
        "certification_id": "0bfd66d529a55807",
        "publisher_id": "16114",
        "relationship": "RESELLER",
        "duplicated": false,
        "line": 205,
        "faults": [],
        "domain": "rubiconproject.com"
      },
      {
        "certification_id": "0bfd66d529a55807",
        "publisher_id": "16422",
        "relationship": "RESELLER",
        "duplicated": false,
        "line": 206,
        "faults": [],
        "domain": "rubiconproject.com"
      },
      {
        "certification_id": "0bfd66d529a55807",
        "publisher_id": "17130",
        "relationship": "RESELLER",
        "duplicated": false,
        "line": 207,
        "faults": [],
        "domain": "rubiconproject.com"
      },
      {
        "certification_id": "0bfd66d529a55807",
        "publisher_id": "17204",
        "relationship": "RESELLER",
        "duplicated": false,
        "line": 208,
        "faults": [],
        "domain": "rubiconproject.com"
      },
      {
        "certification_id": "0bfd66d529a55807",
        "publisher_id": "19668",
        "relationship": "RESELLER",
        "duplicated": false,
        "line": 209,
        "faults": [],
        "domain": "rubiconproject.com"
      },
      {
        "certification_id": "0bfd66d529a55807",
        "publisher_id": "20736",
        "relationship": "RESELLER",
        "duplicated": false,
        "line": 210,
        "faults": [],
        "domain": "rubiconproject.com"
      },
      {
        "certification_id": "0bfd66d529a55807",
        "publisher_id": "208016",
        "relationship": "RESELLER",
        "duplicated": false,
        "line": 211,
        "faults": [],
        "domain": "rubiconproject.com"
      },
      {
        "certification_id": "0bfd66d529a55807",
        "publisher_id": "211211",
        "relationship": "RESELLER",
        "duplicated": false,
        "line": 212,
        "faults": [],
        "domain": "rubiconproject.com"
      },
      {
        "certification_id": "0bfd66d529a55807",
        "publisher_id": "9585",
        "relationship": "RESELLER",
        "duplicated": false,
        "line": 213,
        "faults": [],
        "domain": "rubiconproject.com"
      },
      {
        "certification_id": "b6b21d256ef43532",
        "publisher_id": "19712",
        "relationship": "DIRECT",
        "num_faults": 1,
        "duplicated": false,
        "line": 214,
        "faults": [
          {
            "level": 2,
            "reason": "Domain: Must be in lower case: Sekindo.com",
            "hint": "sekindo.com"
          }
        ],
        "domain": "Sekindo.com"
      },
      {
        "certification_id": null,
        "publisher_id": "13",
        "relationship": "DIRECT",
        "duplicated": false,
        "line": 215,
        "faults": [],
        "domain": "smartadserver.com"
      },
      {
        "certification_id": null,
        "publisher_id": "1338",
        "relationship": "RESELLER",
        "duplicated": false,
        "line": 216,
        "faults": [],
        "domain": "smartadserver.com"
      },
      {
        "certification_id": null,
        "publisher_id": "1827",
        "relationship": "RESELLER",
        "duplicated": false,
        "line": 217,
        "faults": [],
        "domain": "smartadserver.com"
      },
      {
        "certification_id": null,
        "publisher_id": "3063",
        "relationship": "DIRECT",
        "duplicated": false,
        "line": 218,
        "faults": [],
        "domain": "smartadserver.com"
      },
      {
        "certification_id": null,
        "publisher_id": "3245",
        "relationship": "DIRECT",
        "duplicated": false,
        "line": 219,
        "faults": [],
        "domain": "smartadserver.com"
      },
      {
        "certification_id": null,
        "publisher_id": "886",
        "relationship": "RESELLER",
        "duplicated": false,
        "line": 220,
        "faults": [],
        "domain": "smartadserver.com"
      },
      {
        "certification_id": "fafdf38b16bf6b2b",
        "publisher_id": "257611",
        "relationship": "DIRECT",
        "duplicated": false,
        "line": 221,
        "faults": [],
        "domain": "sovrn.com"
      },
      {
        "certification_id": "7842df1d2fe2db34",
        "publisher_id": "142042",
        "relationship": "RESELLER",
        "duplicated": false,
        "line": 222,
        "faults": [],
        "domain": "spotx.tv"
      },
      {
        "certification_id": "7842df1d2fe2db34",
        "publisher_id": "228597",
        "relationship": "RESELLER",
        "duplicated": false,
        "line": 223,
        "faults": [],
        "domain": "spotx.tv"
      },
      {
        "certification_id": "7842df1d2fe2db34",
        "publisher_id": "230037",
        "relationship": "RESELLER",
        "duplicated": false,
        "line": 224,
        "faults": [],
        "domain": "spotx.tv"
      },
      {
        "certification_id": "7842df1d2fe2db34",
        "publisher_id": "238936",
        "relationship": "RESELLER",
        "duplicated": false,
        "line": 225,
        "faults": [],
        "domain": "spotx.tv"
      },
      {
        "certification_id": "7842df1d2fe2db34",
        "publisher_id": "241646",
        "relationship": "RESELLER",
        "duplicated": false,
        "line": 226,
        "faults": [],
        "domain": "spotx.tv"
      },
      {
        "certification_id": "7842df1d2fe2db34",
        "publisher_id": "142042",
        "relationship": "RESELLER",
        "duplicated": false,
        "line": 227,
        "faults": [],
        "domain": "spotxchange.com"
      },
      {
        "certification_id": null,
        "publisher_id": "225721",
        "relationship": "RESELLER",
        "duplicated": false,
        "line": 228,
        "faults": [],
        "domain": "spotxchange.com"
      },
      {
        "certification_id": "7842df1d2fe2db34",
        "publisher_id": "228597",
        "relationship": "RESELLER",
        "duplicated": false,
        "line": 229,
        "faults": [],
        "domain": "spotxchange.com"
      },
      {
        "certification_id": "7842df1d2fe2db34",
        "publisher_id": "230037",
        "relationship": "RESELLER",
        "duplicated": false,
        "line": 230,
        "faults": [],
        "domain": "spotxchange.com"
      },
      {
        "certification_id": "7842df1d2fe2db34",
        "publisher_id": "238936",
        "relationship": "RESELLER",
        "duplicated": false,
        "line": 231,
        "faults": [],
        "domain": "spotxchange.com"
      },
      {
        "certification_id": "7842df1d2fe2db34",
        "publisher_id": "241646",
        "relationship": "RESELLER",
        "duplicated": false,
        "line": 232,
        "faults": [],
        "domain": "spotxchange.com"
      },
      {
        "certification_id": "15a9c44f6d26cbe1",
        "publisher_id": "15429",
        "relationship": "RESELLER",
        "duplicated": false,
        "line": 233,
        "faults": [],
        "domain": "teads.tv"
      },
      {
        "certification_id": "15a9c44f6d26cbe1",
        "publisher_id": "2727",
        "relationship": "DIRECT",
        "duplicated": false,
        "line": 234,
        "faults": [],
        "domain": "teads.tv"
      },
      {
        "certification_id": "15a9c44f6d26cbe1",
        "publisher_id": "6053",
        "relationship": "DIRECT",
        "duplicated": false,
        "line": 235,
        "faults": [],
        "domain": "teads.tv"
      },
      {
        "certification_id": "15a9c44f6d26cbe1",
        "publisher_id": "9965",
        "relationship": "DIRECT",
        "duplicated": false,
        "line": 236,
        "faults": [],
        "domain": "teads.tv"
      },
      {
        "certification_id": "35d5010d7789b49d",
        "publisher_id": "NB56PT",
        "relationship": "DIRECT",
        "duplicated": false,
        "line": 237,
        "faults": [],
        "domain": "themediagrid.com"
      },
      {
        "certification_id": "1a4e959a1b50034a",
        "publisher_id": "ewut4-b6zwq",
        "relationship": "RESELLER",
        "duplicated": false,
        "line": 238,
        "faults": [],
        "domain": "tremorhub.com"
      },
      {
        "certification_id": "1a4e959a1b50034a",
        "publisher_id": "q017o-78mlk",
        "relationship": "RESELLER",
        "duplicated": false,
        "line": 239,
        "faults": [],
        "domain": "tremorhub.com"
      },
      {
        "certification_id": "6c33edb13117fd86",
        "publisher_id": "3355",
        "relationship": "RESELLER",
        "duplicated": false,
        "line": 240,
        "faults": [],
        "domain": "triplelift.com"
      },
      {
        "certification_id": "6c33edb13117fd86",
        "publisher_id": "7277",
        "relationship": "DIRECT",
        "duplicated": false,
        "line": 241,
        "faults": [],
        "domain": "triplelift.com"
      },
      {
        "certification_id": null,
        "publisher_id": "8212",
        "relationship": "DIRECT",
        "num_faults": 1,
        "duplicated": false,
        "line": 245,
        "faults": [
          {
            "level": 3,
            "reason": "Domain: Unexpected format: baddomain",
            "hint": null
          }
        ],
        "domain": "baddomain"
      },
      {
        "certification_id": "f6313b",
        "publisher_id": "878798424",
        "relationship": "UNKNOWN",
        "num_faults": 2,
        "duplicated": false,
        "line": 246,
        "faults": [
          {
            "level": 3,
            "reason": "Unexpected value: UNKNOWN (for: relationship)",
            "hint": [
              "DIRECT",
              "RESELLER"
            ]
          },
          {
            "level": 3,
            "reason": "Domain: Unexpected format: baddomainagain",
            "hint": null
          }
        ],
        "domain": "baddomainagain"
      },
      {
        "certification_id": "f6313b",
        "publisher_id": "878798424",
        "relationship": "UNKNOWN",
        "num_faults": 2,
        "duplicated": true,
        "line": 247,
        "faults": [
          {
            "level": 3,
            "reason": "Unexpected value: UNKNOWN (for: relationship)",
            "hint": [
              "DIRECT",
              "RESELLER"
            ]
          },
          {
            "level": 3,
            "reason": "Domain: Unexpected format: baddomainagain",
            "hint": null
          }
        ],
        "domain": "baddomainagain"
      },
      {
        "certification_id": "",
        "publisher_id": "and",
        "relationship": "that",
        "num_faults": 2,
        "duplicated": false,
        "line": 253,
        "faults": [
          {
            "level": 3,
            "reason": "Unexpected value: THAT (for: relationship)",
            "hint": [
              "DIRECT",
              "RESELLER"
            ]
          },
          {
            "level": 3,
            "reason": "Domain: Unexpected format: justthis",
            "hint": null
          }
        ],
        "domain": "justthis"
      },
      {
        "certification_id": "",
        "publisher_id": "that",
        "relationship": "",
        "num_faults": 2,
        "duplicated": false,
        "line": 255,
        "faults": [
          {
            "level": 3,
            "reason": "Field is mandatory: relationship",
            "hint": [
              "DIRECT",
              "RESELLER"
            ]
          },
          {
            "level": 3,
            "reason": "Domain: Unexpected format: and",
            "hint": null
          }
        ],
        "domain": "and"
      },
      {
        "certification_id": null,
        "publisher_id": "1773068026",
        "relationship": "",
        "num_faults": 1,
        "duplicated": false,
        "line": 257,
        "faults": [
          {
            "level": 3,
            "reason": "Field is mandatory: relationship",
            "hint": [
              "DIRECT",
              "RESELLER"
            ]
          }
        ],
        "domain": "vidazoo.com"
      },
      {
        "certification_id": null,
        "publisher_id": "badvalue",
        "relationship": "3167361",
        "num_faults": 1,
        "duplicated": false,
        "line": 262,
        "faults": [
          {
            "level": 3,
            "reason": "Unexpected value: 3167361 (for: relationship)",
            "hint": [
              "DIRECT",
              "RESELLER"
            ]
          }
        ],
        "domain": "demo.fr"
      }
    ],
    "vars": [
      {
        "value": "andthat",
        "num_faults": 1,
        "duplicated": false,
        "line": 251,
        "faults": [
          {
            "level": 3,
            "reason": "Unexpected value: JUSTTHIS (for: value)",
            "hint": [
              "CONTACT",
              "SUBDOMAIN"
            ]
          }
        ],
        "key": "justthis"
      },
      {
        "value": "hello@domain.fr",
        "duplicated": false,
        "line": 258,
        "faults": [],
        "key": "contact"
      },
      {
        "value": "https://domain.fr/contact",
        "duplicated": false,
        "line": 259,
        "faults": [],
        "key": "contact"
      },
      {
        "value": "(+33)010203040506",
        "duplicated": false,
        "line": 260,
        "faults": [],
        "key": "contact"
      },
      {
        "value": "(+33)010203040506",
        "duplicated": true,
        "line": 261,
        "faults": [],
        "key": "contact"
      },
      {
        "value": "anyvalue...",
        "num_faults": 1,
        "duplicated": false,
        "line": 263,
        "faults": [
          {
            "level": 3,
            "reason": "Unexpected value: UNAUTHORIZEDKEY (for: value)",
            "hint": [
              "CONTACT",
              "SUBDOMAIN"
            ]
          }
        ],
        "key": "unauthorizedkey"
      }
    ]
  }
]